Metadata-Version: 2.1
Name: betconnect
Version: 0.2.2
Summary: A betconnect API client
Home-page: https://github.com/betcode-org/betconnect
Author: Oliver Varney
Author-email: oliverashleyvarney@gmail.com
License: MIT
Classifier: License :: OSI Approved :: MIT License
Classifier: Operating System :: OS Independent
Classifier: Programming Language :: Python :: 3.8
Classifier: Programming Language :: Python :: 3.9
Classifier: Programming Language :: Python :: 3.10
Classifier: Programming Language :: Python :: 3.11
License-File: LICENSE
